Test_CPU_parallel-1.0.5.data/scripts/test_CPU_parallel.py
test_CPU_parallel/__init__.py
test_CPU_parallel/test_CPU_parallel.py
Test_CPU_parallel-1.0.5.dist-info/METADATA
Test_CPU_parallel-1.0.5.dist-info/WHEEL
Test_CPU_parallel-1.0.5.dist-info/top_level.txt
Test_CPU_parallel-1.0.5.dist-info/RECORD
